NuclearTools/MD.cp37-win_amd64.pyd
NuclearTools/MD2D.cp37-win_amd64.pyd
NuclearTools/MD3D.cp37-win_amd64.pyd
NuclearTools/MassFlux.py
NuclearTools/Molecular_Dynamics.py
NuclearTools/Natural_Circulation_SMR.py
NuclearTools/Nuclide_Data.txt
NuclearTools/ThermalHydraulics.py
NuclearTools/Tools.py
NuclearTools/__init__.py
NuclearTools-0.0.609.dist-info/LICENSE.txt
NuclearTools-0.0.609.dist-info/METADATA
NuclearTools-0.0.609.dist-info/WHEEL
NuclearTools-0.0.609.dist-info/top_level.txt
NuclearTools-0.0.609.dist-info/RECORD
