Metadata-Version: 2.1
Name: NuclearTools
Version: 0.0.609
Summary: Handy nuclear tools for quick calculation and reference
Home-page: https://github.com/jablevin/NuclearTools
Author: Jacob Blevins
License: MIT
Platform: UNKNOWN
Classifier: License :: OSI Approved :: MIT License
Classifier: Programming Language :: Python
Classifier: Programming Language :: Python :: 3
Classifier: Programming Language :: Python :: 3.6
Classifier: Programming Language :: Python :: Implementation :: CPython
Classifier: Programming Language :: Python :: Implementation :: PyPy
Requires-Python: >=3.6.0
Requires-Dist: pint
Requires-Dist: numpy
Requires-Dist: datetime
Requires-Dist: matplotlib
Requires-Dist: iapws
Requires-Dist: scipy
